sega_learn/__init__.py
sega_learn/setup.py
sega_learn/auto/__init__.py
sega_learn/auto/classifier.py
sega_learn/auto/regressor.py
sega_learn/clustering/__init__.py
sega_learn/clustering/_dbscan_jit_utils.py
sega_learn/clustering/clustering.py
sega_learn/linear_models/__init__.py
sega_learn/linear_models/_lasso_jit_utils.py
sega_learn/linear_models/_ridge_jit_utils.py
sega_learn/linear_models/classifiers.py
sega_learn/linear_models/regressors.py
sega_learn/nearest_neighbors/__init__.py
sega_learn/nearest_neighbors/_nearest_neighbors_jit_utils.py
sega_learn/nearest_neighbors/base.py
sega_learn/nearest_neighbors/knn_classifier.py
sega_learn/nearest_neighbors/knn_regressor.py
sega_learn/neural_networks/__init__.py
sega_learn/neural_networks/activations.py
sega_learn/neural_networks/animation.py
sega_learn/neural_networks/cupy_utils.py
sega_learn/neural_networks/layers.py
sega_learn/neural_networks/layers_cupy.py
sega_learn/neural_networks/layers_jit.py
sega_learn/neural_networks/loss.py
sega_learn/neural_networks/loss_cupy.py
sega_learn/neural_networks/loss_jit.py
sega_learn/neural_networks/neuralNetworkBase.py
sega_learn/neural_networks/neuralNetworkBaseBackend.py
sega_learn/neural_networks/neuralNetworkCuPyBackend.py
sega_learn/neural_networks/neuralNetworkNumbaBackend.py
sega_learn/neural_networks/numba_utils.py
sega_learn/neural_networks/optimizers.py
sega_learn/neural_networks/optimizers_cupy.py
sega_learn/neural_networks/optimizers_jit.py
sega_learn/neural_networks/schedulers.py
sega_learn/neural_networks_cupy_dev/__init__.py
sega_learn/neural_networks_cupy_dev/cupy_utils.py
sega_learn/neural_networks_cupy_dev/loss.py
sega_learn/neural_networks_cupy_dev/neuralNetwork.py
sega_learn/neural_networks_cupy_dev/optimizers.py
sega_learn/neural_networks_cupy_dev/schedulers.py
sega_learn/neural_networks_numba_dev/__init__.py
sega_learn/neural_networks_numba_dev/layer_jit_utils.py
sega_learn/neural_networks_numba_dev/layers_jit_unified.py
sega_learn-0.1.12.dist-info/licenses/LICENSE.txt
sega_learn-0.1.12.dist-info/METADATA
sega_learn-0.1.12.dist-info/WHEEL
sega_learn-0.1.12.dist-info/top_level.txt
sega_learn-0.1.12.dist-info/RECORD
