Metadata-Version: 2.4
Name: sega_learn
Version: 0.1.12
Summary: Sega Learn is a Python package for machine learning and data science.
Author-email: Santiago Gonzalez <sega97@gmail.com>
License: MIT License
Project-URL: Homepage, https://github.com/SantiagoEnriqueGA/sega_learn
Project-URL: Repository, https://github.com/SantiagoEnriqueGA/sega_learn
Classifier: Programming Language :: Python :: 3
Classifier: Programming Language :: Python :: 3.9
Classifier: Programming Language :: Python :: 3.10
Classifier: Programming Language :: Python :: 3.11
Classifier: Programming Language :: Python :: 3.12
Classifier: License :: OSI Approved :: MIT License
Classifier: Operating System :: OS Independent
Classifier: Development Status :: 3 - Alpha
Classifier: Intended Audience :: Developers
Classifier: Intended Audience :: Science/Research
Classifier: Topic :: Scientific/Engineering :: Artificial Intelligence
Classifier: Topic :: Software Development :: Libraries :: Python Modules
Requires-Python: >=3.9
License-File: LICENSE.txt
Requires-Dist: numpy
Requires-Dist: pandas
Requires-Dist: scikit-learn
Requires-Dist: scipy
Requires-Dist: statsmodels
Provides-Extra: vis
Requires-Dist: matplotlib; extra == "vis"
Requires-Dist: seaborn; extra == "vis"
Requires-Dist: tqdm; extra == "vis"
Requires-Dist: tabulate; extra == "vis"
Provides-Extra: accelerators
Requires-Dist: cupy-cuda12x>=13.4.0; extra == "accelerators"
Requires-Dist: numba>=0.60.0; extra == "accelerators"
Dynamic: license-file
